ALU32_PROJ.v
module flag(clk,carry,in,out);
// flag register give 5 bit output  carry,zero, and three user defined flag
input[31:0] in;
output reg[1:0] out;
input carry,clk;

always@(posedge clk)
begin
if(in==32'h00000000)
begin
out=2'b10;
end
else
begin
out=2'b00;
end

out[1]=carry;

end
endmodule

module ALU(en,clk,op1,op2,mode,dataout,carry,flagout);
input clk,en;
input[31:0] op1,op2;
input [3:0] mode;
output reg [31:0] dataout;
output reg carry;
output wire [1:0]flagout;

flag fl(clk,carry,dataout,flagout);
always@(posedge clk)
if(en==1'b1)
begin
  //addition
  if(mode==4'b0001)
  begin
  {carry,dataout} = {1'b0,op1} + {1'b0,op2};
  end
  //subtraction
  else if(mode==4'b0010)
  begin
 {carry,dataout} = {1'b0,op1} - {1'b0,op2};
  end
  //and
  else if(mode==4'b0011)
  begin
  dataout=op1&op2; 
  end
  //or
  else if(mode==4'b0100)
  begin
  dataout=op1|op2; 
  end
  //complement
  else if(mode==4'b0101)
  begin
  dataout=~op1; 
  end
  //rightshift
  else if(mode==4'b0110)
  begin
  dataout={op1[0],op1[31:1]};
  end
  //leftshift
  else if(mode==4'b0111)
  begin
  dataout={op1[30:0],op1[31]};
  end
  


end




endmodule


module testALU;
reg en,clk;
wire carry;
wire [31:0] dataout;
reg [31:0] op1,op2;
reg[3:0] mode;
wire [1:0] flagout;

ALU st(en,clk,op1,op2,mode,dataout,carry,flagout);

initial
begin
$dumpfile("regalu.vcd");
$dumpvars(0,testALU);
$monitor("%d %d %d %d %d %d",$time,op1,op2,dataout,carry,flagout);
clk=1;
en=1;

//addition
op1=32'hFFFFFFFF;
op2=1;
mode=4'b0001;

#5

//subtraction
op1=05;
op2=01;
mode=4'b0010;

#5

//AND
op1=5;
op2=1;
mode=4'b0011; 

#5

//OR
op1=2;
op2=1;
mode=4'b0100; 

#5

//COMPLEMENT
op1=32'h00000000;
mode=4'b0101;

#5
//RIGHT SHIFT
op1=32'h00000001;
mode=4'b0110;

//LEFT SHIFT
#5
op1=32'h7FFFFFFF;
mode=4'b0111;
#5




$finish;
end
always
begin
#2 clk=~clk;
end

endmodule
//iverilog -o alu.vvp ALU32_PROJ.v

regalu.vcd
$date
	Sun Jun 09 15:03:25 2019
$end
$version
	Icarus Verilog
$end
$timescale
	1s
$end
$scope module testALU $end
$var wire 2 ! flagout [1:0] $end
$var wire 32 " dataout [31:0] $end
$var wire 1 # carry $end
$var reg 1 $ clk $end
$var reg 1 % en $end
$var reg 4 & mode [3:0] $end
$var reg 32 ' op1 [31:0] $end
$var reg 32 ( op2 [31:0] $end
$scope module st $end
$var wire 1 $ clk $end
$var wire 1 % en $end
$var wire 4 ) mode [3:0] $end
$var wire 32 * op1 [31:0] $end
$var wire 32 + op2 [31:0] $end
$var wire 2 , flagout [1:0] $end
$var reg 1 # carry $end
$var reg 32 - dataout [31:0] $end
$scope module fl $end
$var wire 1 # carry $end
$var wire 1 $ clk $end
$var wire 32 . in [31:0] $end
$var reg 2 / out [1:0] $end
$upscope $end
$upscope $end
$upscope $end
$enddefinitions $end
#0
$dumpvars
b10 /
b0 .
b0 -
b10 ,
b1 +
b11111111111111111111111111111111 *
b1 )
b1 (
b11111111111111111111111111111111 '
b1 &
1%
1$
1#
b0 "
b10 !
$end
#2
0$
#4
1$
#5
b10 &
b10 )
b101 '
b101 *
#6
0$
#8
b0 !
b0 ,
b0 /
0#
b100 "
b100 -
b100 .
1$
#10
0$
b11 &
b11 )
#12
b1 "
b1 -
b1 .
1$
#14
0$
#15
b100 &
b100 )
b10 '
b10 *
#16
b11 "
b11 -
b11 .
1$
#18
0$
#20
b11111111111111111111111111111111 "
b11111111111111111111111111111111 -
b11111111111111111111111111111111 .
1$
b101 &
b101 )
b0 '
b0 *
#22
0$
#24
1$
#25
b110 &
b110 )
b1 '
b1 *
#26
0$
#28
b10000000000000000000000000000000 "
b10000000000000000000000000000000 -
b10000000000000000000000000000000 .
1$
#30
0$
b111 &
b111 )
b1111111111111111111111111111111 '
b1111111111111111111111111111111 *
#32
b11111111111111111111111111111110 "
b11111111111111111111111111111110 -
b11111111111111111111111111111110 .
1$
